<?xml version="1.0" encoding="UTF-8"?>
<!DOCTYPE plist PUBLIC "-//Apple//DTD PLIST 1.0//EN" "http://www.apple.com/DTDs/PropertyList-1.0.dtd">
<plist version="1.0">
<dict>
	<key>author</key>
	<string></string>
	<key>comments</key>
	<string></string>
	<key>isUsingConstrainedLayout</key>
	<true/>
	<key>keywords</key>
	<string></string>
	<key>mindMap</key>
	<dict>
		<key>associations</key>
		<array/>
		<key>color</key>
		<string>{0.016, 0.127, 0.160, 1.000}</string>
		<key>mainNodes</key>
		<array>
			<dict>
				<key>contentAlignment</key>
				<integer>1</integer>
				<key>fillColor</key>
				<string>{0.037, 0.160, 0.198, 1.000}</string>
				<key>isDecreasingBranchThickness</key>
				<true/>
				<key>isDrawingFill</key>
				<true/>
				<key>isLeftAligned</key>
				<false/>
				<key>location</key>
				<string>{0, 0}</string>
				<key>nodeID</key>
				<string>4BBD0A33-AAEF-4AEA-9DA0-B64A226488CC</string>
				<key>strokeColor</key>
				<string>{0.273, 0.357, 0.383, 1.000}</string>
				<key>strokeStyle</key>
				<integer>0</integer>
				<key>strokeWidth</key>
				<real>2</real>
				<key>subnodes</key>
				<array>
					<dict>
						<key>contentAlignment</key>
						<integer>1</integer>
						<key>fillColor</key>
						<string>{0.037, 0.160, 0.198, 1.000}</string>
						<key>isDecreasingBranchThickness</key>
						<true/>
						<key>isDrawingFill</key>
						<false/>
						<key>isLeftAligned</key>
						<false/>
						<key>location</key>
						<string>{143, -190}</string>
						<key>nodeID</key>
						<string>8CC66103-61BD-4F40-BA8D-5BC4CE2272CE</string>
						<key>strokeColor</key>
						<string>{0.147, 0.571, 0.525, 1.000}</string>
						<key>strokeStyle</key>
						<integer>0</integer>
						<key>strokeWidth</key>
						<real>6</real>
						<key>subnodes</key>
						<array/>
						<key>title</key>
						<dict>
							<key>constrainedWidth</key>
							<integer>300</integer>
							<key>htmlText</key>
							<string>&lt;p style='color: rgba(251, 244, 220, 1.000000); font: 14px "PingFang SC"; text-align: left; -cocoa-font-postscriptname: "PingFangSC-Regular"; '&gt;天米汽车（宜惠）&lt;/p&gt;</string>
							<key>shrinkToFitContent</key>
							<integer>1</integer>
							<key>text</key>
							<string>{\rtf1\ansi\ansicpg936\cocoartf1504\cocoasubrtf760
{\fonttbl\f0\fnil\fcharset134 PingFangSC-Regular;}
{\colortbl;\red255\green255\blue255;\red251\green244\blue220;}
{\*\expandedcolortbl;;\csgenericrgb\c98500\c95800\c86400;}
\pard\tx560\tx1120\tx1680\tx2240\tx2800\tx3360\tx3920\tx4480\tx5040\tx5600\tx6160\tx6720\pardirnatural

\f0\fs28 \cf2 \'cc\'ec\'c3\'d7\'c6\'fb\'b3\'b5\'a3\'a8\'d2\'cb\'bb\'dd\'a3\'a9}</string>
						</dict>
					</dict>
					<dict>
						<key>contentAlignment</key>
						<integer>1</integer>
						<key>fillColor</key>
						<string>{0.037, 0.160, 0.198, 1.000}</string>
						<key>isDecreasingBranchThickness</key>
						<true/>
						<key>isDrawingFill</key>
						<false/>
						<key>isLeftAligned</key>
						<false/>
						<key>location</key>
						<string>{143, -100}</string>
						<key>nodeID</key>
						<string>56B0C3CB-7DB5-4359-9F42-1EF8BC24C4E1</string>
						<key>strokeColor</key>
						<string>{0.647, 0.468, 0.027, 1.000}</string>
						<key>strokeStyle</key>
						<integer>0</integer>
						<key>strokeWidth</key>
						<real>6</real>
						<key>subnodes</key>
						<array>
							<dict>
								<key>contentAlignment</key>
								<integer>1</integer>
								<key>fillColor</key>
								<string>{0.037, 0.160, 0.198, 1.000}</string>
								<key>isDecreasingBranchThickness</key>
								<true/>
								<key>isDrawingFill</key>
								<false/>
								<key>isLeftAligned</key>
								<false/>
								<key>location</key>
								<string>{255, -154}</string>
								<key>nodeID</key>
								<string>69EFA296-4C45-4CC3-8BF4-37244C94B81D</string>
								<key>strokeColor</key>
								<string>{0.647, 0.468, 0.027, 1.000}</string>
								<key>strokeStyle</key>
								<integer>0</integer>
								<key>strokeWidth</key>
								<real>5</real>
								<key>subnodes</key>
								<array/>
								<key>title</key>
								<dict>
									<key>constrainedWidth</key>
									<integer>300</integer>
									<key>htmlText</key>
									<string>&lt;p style='color: rgba(251, 244, 220, 1.000000); font: 14px "PingFang SC"; text-align: left; -cocoa-font-postscriptname: "PingFangSC-Regular"; '&gt;车型&lt;/p&gt;</string>
									<key>shrinkToFitContent</key>
									<integer>1</integer>
									<key>text</key>
									<string>{\rtf1\ansi\ansicpg936\cocoartf1504\cocoasubrtf760
{\fonttbl\f0\fnil\fcharset134 PingFangSC-Regular;}
{\colortbl;\red255\green255\blue255;\red251\green244\blue220;}
{\*\expandedcolortbl;;\csgenericrgb\c98500\c95800\c86400;}
\pard\tx560\tx1120\tx1680\tx2240\tx2800\tx3360\tx3920\tx4480\tx5040\tx5600\tx6160\tx6720\pardirnatural

\f0\fs28 \cf2 \'b3\'b5\'d0\'cd}</string>
								</dict>
							</dict>
							<dict>
								<key>contentAlignment</key>
								<integer>1</integer>
								<key>fillColor</key>
								<string>{0.037, 0.160, 0.198, 1.000}</string>
								<key>isDecreasingBranchThickness</key>
								<true/>
								<key>isDrawingFill</key>
								<false/>
								<key>isLeftAligned</key>
								<false/>
								<key>location</key>
								<string>{255, -118}</string>
								<key>nodeID</key>
								<string>FF9B35FD-60AC-4DDE-B3E7-7701198B0BF9</string>
								<key>strokeColor</key>
								<string>{0.647, 0.468, 0.027, 1.000}</string>
								<key>strokeStyle</key>
								<integer>0</integer>
								<key>strokeWidth</key>
								<real>5</real>
								<key>subnodes</key>
								<array/>
								<key>title</key>
								<dict>
									<key>constrainedWidth</key>
									<integer>300</integer>
									<key>htmlText</key>
									<string>&lt;p style='color: rgba(251, 244, 220, 1.000000); font: 14px "PingFang SC"; text-align: left; -cocoa-font-postscriptname: "PingFangSC-Regular"; '&gt;车价&lt;/p&gt;</string>
									<key>shrinkToFitContent</key>
									<integer>1</integer>
									<key>text</key>
									<string>{\rtf1\ansi\ansicpg936\cocoartf1504\cocoasubrtf760
{\fonttbl\f0\fnil\fcharset134 PingFangSC-Regular;}
{\colortbl;\red255\green255\blue255;\red251\green244\blue220;}
{\*\expandedcolortbl;;\csgenericrgb\c98500\c95800\c86400;}
\pard\tx560\tx1120\tx1680\tx2240\tx2800\tx3360\tx3920\tx4480\tx5040\tx5600\tx6160\tx6720\pardirnatural

\f0\fs28 \cf2 \'b3\'b5\'bc\'db}</string>
								</dict>
							</dict>
							<dict>
								<key>contentAlignment</key>
								<integer>1</integer>
								<key>fillColor</key>
								<string>{0.037, 0.160, 0.198, 1.000}</string>
								<key>isDecreasingBranchThickness</key>
								<true/>
								<key>isDrawingFill</key>
								<false/>
								<key>isLeftAligned</key>
								<false/>
								<key>location</key>
								<string>{255, -82}</string>
								<key>nodeID</key>
								<string>FE5B0B99-C605-41FF-88F5-81B572CA33CA</string>
								<key>strokeColor</key>
								<string>{0.647, 0.468, 0.027, 1.000}</string>
								<key>strokeStyle</key>
								<integer>0</integer>
								<key>strokeWidth</key>
								<real>5</real>
								<key>subnodes</key>
								<array/>
								<key>title</key>
								<dict>
									<key>constrainedWidth</key>
									<integer>300</integer>
									<key>htmlText</key>
									<string>&lt;p style='color: rgba(251, 244, 220, 1.000000); font: 14px "PingFang SC"; text-align: left; -cocoa-font-postscriptname: "PingFangSC-Regular"; '&gt;首付&lt;/p&gt;</string>
									<key>shrinkToFitContent</key>
									<integer>1</integer>
									<key>text</key>
									<string>{\rtf1\ansi\ansicpg936\cocoartf1504\cocoasubrtf760
{\fonttbl\f0\fnil\fcharset134 PingFangSC-Regular;}
{\colortbl;\red255\green255\blue255;\red251\green244\blue220;}
{\*\expandedcolortbl;;\csgenericrgb\c98500\c95800\c86400;}
\pard\tx560\tx1120\tx1680\tx2240\tx2800\tx3360\tx3920\tx4480\tx5040\tx5600\tx6160\tx6720\pardirnatural

\f0\fs28 \cf2 \'ca\'d7\'b8\'b6}</string>
								</dict>
							</dict>
							<dict>
								<key>contentAlignment</key>
								<integer>1</integer>
								<key>fillColor</key>
								<string>{0.037, 0.160, 0.198, 1.000}</string>
								<key>isDecreasingBranchThickness</key>
								<true/>
								<key>isDrawingFill</key>
								<false/>
								<key>isLeftAligned</key>
								<false/>
								<key>location</key>
								<string>{255, -46}</string>
								<key>nodeID</key>
								<string>22B70E48-A886-444E-9DF3-FF6B08C83893</string>
								<key>strokeColor</key>
								<string>{0.647, 0.468, 0.027, 1.000}</string>
								<key>strokeStyle</key>
								<integer>0</integer>
								<key>strokeWidth</key>
								<real>5</real>
								<key>subnodes</key>
								<array/>
								<key>title</key>
								<dict>
									<key>constrainedWidth</key>
									<integer>300</integer>
									<key>htmlText</key>
									<string>&lt;p style='color: rgba(251, 244, 220, 1.000000); font: 14px "PingFang SC"; text-align: left; -cocoa-font-postscriptname: "PingFangSC-Regular"; '&gt;期限&lt;/p&gt;</string>
									<key>shrinkToFitContent</key>
									<integer>1</integer>
									<key>text</key>
									<string>{\rtf1\ansi\ansicpg936\cocoartf1504\cocoasubrtf760
{\fonttbl\f0\fnil\fcharset134 PingFangSC-Regular;}
{\colortbl;\red255\green255\blue255;\red251\green244\blue220;}
{\*\expandedcolortbl;;\csgenericrgb\c98500\c95800\c86400;}
\pard\tx560\tx1120\tx1680\tx2240\tx2800\tx3360\tx3920\tx4480\tx5040\tx5600\tx6160\tx6720\pardirnatural

\f0\fs28 \cf2 \'c6\'da\'cf\'de}</string>
								</dict>
							</dict>
						</array>
						<key>title</key>
						<dict>
							<key>constrainedWidth</key>
							<integer>300</integer>
							<key>htmlText</key>
							<string>&lt;p style='color: rgba(251, 244, 220, 1.000000); font: 14px "PingFang SC"; text-align: left; -cocoa-font-postscriptname: "PingFangSC-Regular"; '&gt;录单&lt;/p&gt;</string>
							<key>shrinkToFitContent</key>
							<integer>1</integer>
							<key>text</key>
							<string>{\rtf1\ansi\ansicpg936\cocoartf1504\cocoasubrtf760
{\fonttbl\f0\fnil\fcharset134 PingFangSC-Regular;}
{\colortbl;\red255\green255\blue255;\red251\green244\blue220;}
{\*\expandedcolortbl;;\csgenericrgb\c98500\c95800\c86400;}
\pard\tx560\tx1120\tx1680\tx2240\tx2800\tx3360\tx3920\tx4480\tx5040\tx5600\tx6160\tx6720\pardirnatural

\f0\fs28 \cf2 \'c2\'bc\'b5\'a5}</string>
						</dict>
					</dict>
					<dict>
						<key>contentAlignment</key>
						<integer>1</integer>
						<key>fillColor</key>
						<string>{0.037, 0.160, 0.198, 1.000}</string>
						<key>isDecreasingBranchThickness</key>
						<true/>
						<key>isDrawingFill</key>
						<false/>
						<key>isLeftAligned</key>
						<false/>
						<key>location</key>
						<string>{143, -10}</string>
						<key>nodeID</key>
						<string>007EFF50-0BC1-4102-929D-89FD61066177</string>
						<key>strokeColor</key>
						<string>{0.450, 0.541, 0.020, 1.000}</string>
						<key>strokeStyle</key>
						<integer>0</integer>
						<key>strokeWidth</key>
						<real>6</real>
						<key>subnodes</key>
						<array>
							<dict>
								<key>contentAlignment</key>
								<integer>1</integer>
								<key>fillColor</key>
								<string>{0.037, 0.160, 0.198, 1.000}</string>
								<key>isDecreasingBranchThickness</key>
								<true/>
								<key>isDrawingFill</key>
								<false/>
								<key>isLeftAligned</key>
								<false/>
								<key>location</key>
								<string>{257, -10}</string>
								<key>nodeID</key>
								<string>BA046D83-E37B-4CA1-91FF-3DD69BAD747D</string>
								<key>strokeColor</key>
								<string>{0.450, 0.541, 0.020, 1.000}</string>
								<key>strokeStyle</key>
								<integer>0</integer>
								<key>strokeWidth</key>
								<real>5</real>
								<key>subnodes</key>
								<array>
									<dict>
										<key>contentAlignment</key>
										<integer>1</integer>
										<key>fillColor</key>
										<string>{0.037, 0.160, 0.198, 1.000}</string>
										<key>isDecreasingBranchThickness</key>
										<true/>
										<key>isDrawingFill</key>
										<false/>
										<key>isLeftAligned</key>
										<false/>
										<key>location</key>
										<string>{369, -10}</string>
										<key>nodeID</key>
										<string>1C7D0684-72F7-4007-BCC8-3AD26F9847BA</string>
										<key>strokeColor</key>
										<string>{0.450, 0.541, 0.020, 1.000}</string>
										<key>strokeStyle</key>
										<integer>0</integer>
										<key>strokeWidth</key>
										<real>4</real>
										<key>subnodes</key>
										<array/>
										<key>title</key>
										<dict>
											<key>constrainedWidth</key>
											<integer>300</integer>
											<key>htmlText</key>
											<string>&lt;p style='color: rgba(251, 244, 220, 1.000000); font: 14px "PingFang SC"; text-align: left; -cocoa-font-postscriptname: "PingFangSC-Regular"; '&gt;录单&lt;/p&gt;</string>
											<key>shrinkToFitContent</key>
											<integer>1</integer>
											<key>text</key>
											<string>{\rtf1\ansi\ansicpg936\cocoartf1504\cocoasubrtf760
{\fonttbl\f0\fnil\fcharset134 PingFangSC-Regular;}
{\colortbl;\red255\green255\blue255;\red251\green244\blue220;}
{\*\expandedcolortbl;;\csgenericrgb\c98500\c95800\c86400;}
\pard\tx560\tx1120\tx1680\tx2240\tx2800\tx3360\tx3920\tx4480\tx5040\tx5600\tx6160\tx6720\pardirnatural

\f0\fs28 \cf2 \'c2\'bc\'b5\'a5}</string>
										</dict>
									</dict>
								</array>
								<key>title</key>
								<dict>
									<key>constrainedWidth</key>
									<integer>300</integer>
									<key>htmlText</key>
									<string>&lt;p style='color: rgba(251, 244, 220, 1.000000); font: 14px "PingFang SC"; text-align: left; -cocoa-font-postscriptname: "PingFangSC-Regular"; '&gt;试算&lt;/p&gt;</string>
									<key>shrinkToFitContent</key>
									<integer>1</integer>
									<key>text</key>
									<string>{\rtf1\ansi\ansicpg936\cocoartf1504\cocoasubrtf760
{\fonttbl\f0\fnil\fcharset134 PingFangSC-Regular;}
{\colortbl;\red255\green255\blue255;\red251\green244\blue220;}
{\*\expandedcolortbl;;\csgenericrgb\c98500\c95800\c86400;}
\pard\tx560\tx1120\tx1680\tx2240\tx2800\tx3360\tx3920\tx4480\tx5040\tx5600\tx6160\tx6720\pardirnatural

\f0\fs28 \cf2 \'ca\'d4\'cb\'e3}</string>
								</dict>
							</dict>
						</array>
						<key>title</key>
						<dict>
							<key>constrainedWidth</key>
							<integer>300</integer>
							<key>htmlText</key>
							<string>&lt;p style='color: rgba(251, 244, 220, 1.000000); font: 14px "PingFang SC"; text-align: left; -cocoa-font-postscriptname: "PingFangSC-Regular"; '&gt;车型库&lt;/p&gt;</string>
							<key>shrinkToFitContent</key>
							<integer>1</integer>
							<key>text</key>
							<string>{\rtf1\ansi\ansicpg936\cocoartf1504\cocoasubrtf760
{\fonttbl\f0\fnil\fcharset134 PingFangSC-Regular;}
{\colortbl;\red255\green255\blue255;\red251\green244\blue220;}
{\*\expandedcolortbl;;\csgenericrgb\c98500\c95800\c86400;}
\pard\tx560\tx1120\tx1680\tx2240\tx2800\tx3360\tx3920\tx4480\tx5040\tx5600\tx6160\tx6720\pardirnatural

\f0\fs28 \cf2 \'b3\'b5\'d0\'cd\'bf\'e2}</string>
						</dict>
					</dict>
					<dict>
						<key>contentAlignment</key>
						<integer>1</integer>
						<key>fillColor</key>
						<string>{0.037, 0.160, 0.198, 1.000}</string>
						<key>isDecreasingBranchThickness</key>
						<true/>
						<key>isDrawingFill</key>
						<false/>
						<key>isLeftAligned</key>
						<false/>
						<key>location</key>
						<string>{143, 62}</string>
						<key>nodeID</key>
						<string>C0B815E7-7BFF-40A0-8406-895CE3BF25A3</string>
						<key>strokeColor</key>
						<string>{0.128, 0.463, 0.782, 1.000}</string>
						<key>strokeStyle</key>
						<integer>0</integer>
						<key>strokeWidth</key>
						<real>6</real>
						<key>subnodes</key>
						<array>
							<dict>
								<key>contentAlignment</key>
								<integer>1</integer>
								<key>fillColor</key>
								<string>{0.037, 0.160, 0.198, 1.000}</string>
								<key>isDecreasingBranchThickness</key>
								<true/>
								<key>isDrawingFill</key>
								<false/>
								<key>isLeftAligned</key>
								<false/>
								<key>location</key>
								<string>{271, 26}</string>
								<key>nodeID</key>
								<string>A398F034-1D74-4789-A7CF-2478DF867A4E</string>
								<key>strokeColor</key>
								<string>{0.128, 0.463, 0.782, 1.000}</string>
								<key>strokeStyle</key>
								<integer>0</integer>
								<key>strokeWidth</key>
								<real>5</real>
								<key>subnodes</key>
								<array/>
								<key>title</key>
								<dict>
									<key>constrainedWidth</key>
									<integer>300</integer>
									<key>htmlText</key>
									<string>&lt;p style='color: rgba(251, 244, 220, 1.000000); font: 14px "PingFang SC"; -cocoa-font-postscriptname: "PingFangSC-Regular"; '&gt;申请列表&lt;/p&gt;</string>
									<key>shrinkToFitContent</key>
									<integer>1</integer>
									<key>text</key>
									<string>{\rtf1\ansi\ansicpg936\cocoartf1504\cocoasubrtf760
{\fonttbl\f0\fnil\fcharset134 PingFangSC-Regular;}
{\colortbl;\red255\green255\blue255;\red251\green244\blue220;}
{\*\expandedcolortbl;;\csgenericrgb\c98500\c95800\c86400;}
\pard\tx560\tx1120\tx1680\tx2240\tx2800\tx3360\tx3920\tx4480\tx5040\tx5600\tx6160\tx6720\pardirnatural

\f0\fs28 \cf2 \'c9\'ea\'c7\'eb\'c1\'d0\'b1\'ed}</string>
								</dict>
							</dict>
							<dict>
								<key>contentAlignment</key>
								<integer>1</integer>
								<key>fillColor</key>
								<string>{0.037, 0.160, 0.198, 1.000}</string>
								<key>isDecreasingBranchThickness</key>
								<true/>
								<key>isDrawingFill</key>
								<false/>
								<key>isLeftAligned</key>
								<false/>
								<key>location</key>
								<string>{271, 62}</string>
								<key>nodeID</key>
								<string>C5074466-AB1C-4305-9747-75E290C10C32</string>
								<key>strokeColor</key>
								<string>{0.128, 0.463, 0.782, 1.000}</string>
								<key>strokeStyle</key>
								<integer>0</integer>
								<key>strokeWidth</key>
								<real>5</real>
								<key>subnodes</key>
								<array/>
								<key>title</key>
								<dict>
									<key>constrainedWidth</key>
									<integer>300</integer>
									<key>htmlText</key>
									<string>&lt;p style='color: rgba(251, 244, 220, 1.000000); font: 14px "PingFang SC"; -cocoa-font-postscriptname: "PingFangSC-Regular"; '&gt;申请状态&lt;/p&gt;</string>
									<key>shrinkToFitContent</key>
									<integer>1</integer>
									<key>text</key>
									<string>{\rtf1\ansi\ansicpg936\cocoartf1504\cocoasubrtf760
{\fonttbl\f0\fnil\fcharset134 PingFangSC-Regular;}
{\colortbl;\red255\green255\blue255;\red251\green244\blue220;}
{\*\expandedcolortbl;;\csgenericrgb\c98500\c95800\c86400;}
\pard\tx560\tx1120\tx1680\tx2240\tx2800\tx3360\tx3920\tx4480\tx5040\tx5600\tx6160\tx6720\pardirnatural

\f0\fs28 \cf2 \'c9\'ea\'c7\'eb\'d7\'b4\'cc\'ac}</string>
								</dict>
							</dict>
							<dict>
								<key>contentAlignment</key>
								<integer>1</integer>
								<key>fillColor</key>
								<string>{0.037, 0.160, 0.198, 1.000}</string>
								<key>isDecreasingBranchThickness</key>
								<true/>
								<key>isDrawingFill</key>
								<false/>
								<key>isLeftAligned</key>
								<false/>
								<key>location</key>
								<string>{271, 98}</string>
								<key>nodeID</key>
								<string>0B3E815F-45A5-47F2-A1B8-6617204F118D</string>
								<key>strokeColor</key>
								<string>{0.128, 0.463, 0.782, 1.000}</string>
								<key>strokeStyle</key>
								<integer>0</integer>
								<key>strokeWidth</key>
								<real>5</real>
								<key>subnodes</key>
								<array/>
								<key>title</key>
								<dict>
									<key>constrainedWidth</key>
									<integer>300</integer>
									<key>htmlText</key>
									<string>&lt;p style='color: rgba(251, 244, 220, 1.000000); font: 14px "PingFang SC"; -cocoa-font-postscriptname: "PingFangSC-Regular"; '&gt;申请进度查询&lt;/p&gt;</string>
									<key>shrinkToFitContent</key>
									<integer>1</integer>
									<key>text</key>
									<string>{\rtf1\ansi\ansicpg936\cocoartf1504\cocoasubrtf760
{\fonttbl\f0\fnil\fcharset134 PingFangSC-Regular;}
{\colortbl;\red255\green255\blue255;\red251\green244\blue220;}
{\*\expandedcolortbl;;\csgenericrgb\c98500\c95800\c86400;}
\pard\tx560\tx1120\tx1680\tx2240\tx2800\tx3360\tx3920\tx4480\tx5040\tx5600\tx6160\tx6720\pardirnatural

\f0\fs28 \cf2 \'c9\'ea\'c7\'eb\'bd\'f8\'b6\'c8\'b2\'e9\'d1\'af}</string>
								</dict>
							</dict>
						</array>
						<key>title</key>
						<dict>
							<key>constrainedWidth</key>
							<integer>300</integer>
							<key>htmlText</key>
							<string>&lt;p style='color: rgba(251, 244, 220, 1.000000); font: 14px "PingFang SC"; -cocoa-font-postscriptname: "PingFangSC-Regular"; '&gt;申请查询&lt;/p&gt;</string>
							<key>shrinkToFitContent</key>
							<integer>1</integer>
							<key>text</key>
							<string>{\rtf1\ansi\ansicpg936\cocoartf1504\cocoasubrtf760
{\fonttbl\f0\fnil\fcharset134 PingFangSC-Regular;}
{\colortbl;\red255\green255\blue255;\red251\green244\blue220;}
{\*\expandedcolortbl;;\csgenericrgb\c98500\c95800\c86400;}
\pard\tx560\tx1120\tx1680\tx2240\tx2800\tx3360\tx3920\tx4480\tx5040\tx5600\tx6160\tx6720\pardirnatural

\f0\fs28 \cf2 \'c9\'ea\'c7\'eb\'b2\'e9\'d1\'af}</string>
						</dict>
					</dict>
					<dict>
						<key>contentAlignment</key>
						<integer>1</integer>
						<key>fillColor</key>
						<string>{0.037, 0.160, 0.198, 1.000}</string>
						<key>isDecreasingBranchThickness</key>
						<true/>
						<key>isDrawingFill</key>
						<false/>
						<key>isLeftAligned</key>
						<false/>
						<key>location</key>
						<string>{143, 152}</string>
						<key>nodeID</key>
						<string>F9E11456-8AD4-40FA-9A52-71C1EE14A44A</string>
						<key>strokeColor</key>
						<string>{0.713, 0.331, 0.520, 1.000}</string>
						<key>strokeStyle</key>
						<integer>0</integer>
						<key>strokeWidth</key>
						<real>6</real>
						<key>subnodes</key>
						<array>
							<dict>
								<key>contentAlignment</key>
								<integer>1</integer>
								<key>fillColor</key>
								<string>{0.037, 0.160, 0.198, 1.000}</string>
								<key>isDecreasingBranchThickness</key>
								<true/>
								<key>isDrawingFill</key>
								<false/>
								<key>isLeftAligned</key>
								<false/>
								<key>location</key>
								<string>{271, 134}</string>
								<key>nodeID</key>
								<string>E4BAECBF-C943-4F31-AB9A-8C1DDFB3448D</string>
								<key>strokeColor</key>
								<string>{0.713, 0.331, 0.520, 1.000}</string>
								<key>strokeStyle</key>
								<integer>0</integer>
								<key>strokeWidth</key>
								<real>5</real>
								<key>subnodes</key>
								<array/>
								<key>title</key>
								<dict>
									<key>constrainedWidth</key>
									<integer>300</integer>
									<key>htmlText</key>
									<string>&lt;p style='color: rgba(251, 244, 220, 1.000000); font: 14px "PingFang SC"; -cocoa-font-postscriptname: "PingFangSC-Regular"; '&gt;个人业绩&lt;/p&gt;</string>
									<key>shrinkToFitContent</key>
									<integer>1</integer>
									<key>text</key>
									<string>{\rtf1\ansi\ansicpg936\cocoartf1504\cocoasubrtf760
{\fonttbl\f0\fnil\fcharset134 PingFangSC-Regular;}
{\colortbl;\red255\green255\blue255;\red251\green244\blue220;}
{\*\expandedcolortbl;;\csgenericrgb\c98500\c95800\c86400;}
\pard\tx560\tx1120\tx1680\tx2240\tx2800\tx3360\tx3920\tx4480\tx5040\tx5600\tx6160\tx6720\pardirnatural

\f0\fs28 \cf2 \'b8\'f6\'c8\'cb\'d2\'b5\'bc\'a8}</string>
								</dict>
							</dict>
							<dict>
								<key>contentAlignment</key>
								<integer>1</integer>
								<key>fillColor</key>
								<string>{0.037, 0.160, 0.198, 1.000}</string>
								<key>isDecreasingBranchThickness</key>
								<true/>
								<key>isDrawingFill</key>
								<false/>
								<key>isLeftAligned</key>
								<false/>
								<key>location</key>
								<string>{271, 170}</string>
								<key>nodeID</key>
								<string>9F5AF861-5678-4F98-84AF-F7D862FC665A</string>
								<key>strokeColor</key>
								<string>{0.713, 0.331, 0.520, 1.000}</string>
								<key>strokeStyle</key>
								<integer>0</integer>
								<key>strokeWidth</key>
								<real>5</real>
								<key>subnodes</key>
								<array/>
								<key>title</key>
								<dict>
									<key>constrainedWidth</key>
									<integer>300</integer>
									<key>htmlText</key>
									<string>&lt;p style='color: rgba(251, 244, 220, 1.000000); font: 14px "PingFang SC"; -cocoa-font-postscriptname: "PingFangSC-Regular"; '&gt;下属团队业绩&lt;/p&gt;</string>
									<key>shrinkToFitContent</key>
									<integer>1</integer>
									<key>text</key>
									<string>{\rtf1\ansi\ansicpg936\cocoartf1504\cocoasubrtf760
{\fonttbl\f0\fnil\fcharset134 PingFangSC-Regular;}
{\colortbl;\red255\green255\blue255;\red251\green244\blue220;}
{\*\expandedcolortbl;;\csgenericrgb\c98500\c95800\c86400;}
\pard\tx560\tx1120\tx1680\tx2240\tx2800\tx3360\tx3920\tx4480\tx5040\tx5600\tx6160\tx6720\pardirnatural

\f0\fs28 \cf2 \'cf\'c2\'ca\'f4\'cd\'c5\'b6\'d3\'d2\'b5\'bc\'a8}</string>
								</dict>
							</dict>
						</array>
						<key>title</key>
						<dict>
							<key>constrainedWidth</key>
							<integer>300</integer>
							<key>htmlText</key>
							<string>&lt;p style='color: rgba(251, 244, 220, 1.000000); font: 14px "PingFang SC"; -cocoa-font-postscriptname: "PingFangSC-Regular"; '&gt;业绩查询&lt;/p&gt;</string>
							<key>shrinkToFitContent</key>
							<integer>1</integer>
							<key>text</key>
							<string>{\rtf1\ansi\ansicpg936\cocoartf1504\cocoasubrtf760
{\fonttbl\f0\fnil\fcharset134 PingFangSC-Regular;}
{\colortbl;\red255\green255\blue255;\red251\green244\blue220;}
{\*\expandedcolortbl;;\csgenericrgb\c98500\c95800\c86400;}
\pard\tx560\tx1120\tx1680\tx2240\tx2800\tx3360\tx3920\tx4480\tx5040\tx5600\tx6160\tx6720\pardirnatural

\f0\fs28 \cf2 \'d2\'b5\'bc\'a8\'b2\'e9\'d1\'af}</string>
						</dict>
					</dict>
					<dict>
						<key>contentAlignment</key>
						<integer>1</integer>
						<key>fillColor</key>
						<string>{0.037, 0.160, 0.198, 1.000}</string>
						<key>isDecreasingBranchThickness</key>
						<true/>
						<key>isDrawingFill</key>
						<false/>
						<key>isLeftAligned</key>
						<false/>
						<key>location</key>
						<string>{143, 206}</string>
						<key>nodeID</key>
						<string>179C90A2-89FF-4D99-89D5-224BD0B4009E</string>
						<key>strokeColor</key>
						<string>{0.713, 0.331, 0.520, 1.000}</string>
						<key>strokeStyle</key>
						<integer>0</integer>
						<key>strokeWidth</key>
						<real>6</real>
						<key>subnodes</key>
						<array/>
						<key>title</key>
						<dict>
							<key>constrainedWidth</key>
							<integer>300</integer>
							<key>htmlText</key>
							<string>&lt;p style='color: rgba(251, 244, 220, 1.000000); font: 14px "PingFang SC"; -cocoa-font-postscriptname: "PingFangSC-Regular"; '&gt;消息中心&lt;/p&gt;</string>
							<key>shrinkToFitContent</key>
							<integer>1</integer>
							<key>text</key>
							<string>{\rtf1\ansi\ansicpg936\cocoartf1504\cocoasubrtf760
{\fonttbl\f0\fnil\fcharset134 PingFangSC-Regular;}
{\colortbl;\red255\green255\blue255;\red251\green244\blue220;}
{\*\expandedcolortbl;;\csgenericrgb\c98500\c95800\c86400;}
\pard\tx560\tx1120\tx1680\tx2240\tx2800\tx3360\tx3920\tx4480\tx5040\tx5600\tx6160\tx6720\pardirnatural

\f0\fs28 \cf2 \'cf\'fb\'cf\'a2\'d6\'d0\'d0\'c4}</string>
						</dict>
					</dict>
				</array>
				<key>title</key>
				<dict>
					<key>constrainedWidth</key>
					<integer>300</integer>
					<key>htmlText</key>
					<string>&lt;p style='color: rgba(251, 244, 220, 1.000000); font: 13px "PingFang SC"; -cocoa-font-postscriptname: "PingFangSC-Regular"; '&gt;以租代购&lt;/p&gt;</string>
					<key>shrinkToFitContent</key>
					<integer>1</integer>
					<key>text</key>
					<string>{\rtf1\ansi\ansicpg936\cocoartf1504\cocoasubrtf760
{\fonttbl\f0\fnil\fcharset134 PingFangSC-Regular;}
{\colortbl;\red255\green255\blue255;\red251\green244\blue220;}
{\*\expandedcolortbl;;\csgenericrgb\c98500\c95800\c86400;}
\pard\tx560\tx1120\tx1680\tx2240\tx2800\tx3360\tx3920\tx4480\tx5040\tx5600\tx6160\tx6720\pardirnatural

\f0\fs26 \cf2 \'d2\'d4\'d7\'e2\'b4\'fa\'b9\'ba}</string>
				</dict>
			</dict>
		</array>
	</dict>
	<key>printInfo</key>
	<data>
	BAtzdHJlYW10eXBlZIHoA4QBQISEhAtOU1ByaW50SW5mbwGEhAhOU09iamVjdACFkoSE
	hBNOU011dGFibGVEaWN0aW9uYXJ5AISEDE5TRGljdGlvbmFyeQCUhAFpCJKEhIQITlNT
	dHJpbmcBlIQBKxZOU0hvcml6b250YWxseUNlbnRlcmVkhpKEhIQITlNOdW1iZXIAhIQH
	TlNWYWx1ZQCUhAEqhIQBY50BhpKEmZkNTlNSaWdodE1hcmdpboaShJuchIQBZp5IhpKE
	mZkMTlNMZWZ0TWFyZ2luhpKfkoSZmRVOU0hvcml6b25hbFBhZ2luYXRpb26GkoSbnISX
	lwKGkoSZmRROU1ZlcnRpY2FsUGFnaW5hdGlvboaShJucpJcAhpKEmZkUTlNWZXJ0aWNh
	bGx5Q2VudGVyZWSGkpqShJmZC05TVG9wTWFyZ2luhpKEm5ygnlqGkoSZmQ5OU0JvdHRv
	bU1hcmdpboaSqYaG
	</data>
	<key>title</key>
	<string>以租代购</string>
	<key>version</key>
	<integer>4</integer>
</dict>
</plist>
